hello_robot_stretch_diagnostics-0.0.14.data/scripts/stretch_diagnostic_check.py
stretch_diagnostics/__init__.py
stretch_diagnostics/test_base.py
stretch_diagnostics/test_helpers.py
stretch_diagnostics/test_manager.py
stretch_diagnostics/test_order.py
stretch_diagnostics/test_result.py
stretch_diagnostics/test_runner.py
stretch_diagnostics/test_suite.py
stretch_diagnostics_tests/__init__.py
stretch_diagnostics_tests/arm_tests/test_ARM_effort_through_range_of_motion.py
stretch_diagnostics_tests/cpu_tests/test_CPU_usage_temp.py
stretch_diagnostics_tests/dynamixel_tests/test_DYNAMIXEL_check_zero_position.py
stretch_diagnostics_tests/dynamixel_tests/test_DYNAMIXEL_hardware.py
stretch_diagnostics_tests/dynamixel_tests/test_DYNAMIXEL_measure_efforts.py
stretch_diagnostics_tests/dynamixel_tests/test_DYNAMIXEL_measure_range_of_motion.py
stretch_diagnostics_tests/gripper_tests/test_GRIPPER_broken_string.py
stretch_diagnostics_tests/lift_tests/test_LIFT_effort_through_range_of_motion.py
stretch_diagnostics_tests/power_tests/test_POWER_battery_health.py
stretch_diagnostics_tests/power_tests/test_POWER_battery_loading.py
stretch_diagnostics_tests/power_tests/test_POWER_charger.py
stretch_diagnostics_tests/realsense_tests/test_REALSENSE_cable.py
stretch_diagnostics_tests/realsense_tests/test_REALSENSE_frame_rate.py
stretch_diagnostics_tests/ros_tests/test_ROS_calibration.py
stretch_diagnostics_tests/ros_tests/test_ROS_sourced_distro.py
stretch_diagnostics_tests/ros_tests/test_ROS_urdf.py
stretch_diagnostics_tests/simple_tests/test_SIMPLE_accessories.py
stretch_diagnostics_tests/simple_tests/test_SIMPLE_capture_system.py
stretch_diagnostics_tests/simple_tests/test_SIMPLE_dynamixel_configure.py
stretch_diagnostics_tests/simple_tests/test_SIMPLE_filesystem.py
stretch_diagnostics_tests/simple_tests/test_SIMPLE_firmware.py
stretch_diagnostics_tests/simple_tests/test_SIMPLE_foo.py
stretch_diagnostics_tests/simple_tests/test_SIMPLE_params.py
hello_robot_stretch_diagnostics-0.0.14.dist-info/METADATA
hello_robot_stretch_diagnostics-0.0.14.dist-info/WHEEL
hello_robot_stretch_diagnostics-0.0.14.dist-info/top_level.txt
hello_robot_stretch_diagnostics-0.0.14.dist-info/RECORD
