Metadata-Version: 2.1
Name: hello-robot-stretch-diagnostics
Version: 0.0.14
Summary: Stretch Diagnostics
Home-page: https://github.com/hello-robot/stretch_diagnostics
Author: Hello Robot Inc.
Author-email: support@hello-robot.com
License: UNKNOWN
Platform: UNKNOWN
Classifier: Programming Language :: Python :: 3
Classifier: Operating System :: OS Independent
Classifier: License :: OSI Approved :: GNU General Public License v3 (GPLv3)
Requires-Dist: hello-robot-stretch-body (>=0.4.15)
Requires-Dist: hello-robot-stretch-factory (>=0.3.12)
Requires-Dist: stress
Requires-Dist: xmltodict
